{
  "permission_items": [
    {
      "permissions": [
        "Operator"
      ],
      "excluded_permissions": [],
      "name": "ExternalChannelProfile_List",
      "is_excluded": false,
      "object": null,
      "parameter": null,
      "service": "ExternalChannelProfile",
      "action": null,
      "type": "Action"
    },
    {
      "permissions": [
        "Operator"
      ],
      "excluded_permissions": [],
      "name": "ExternalChannelProfile_Delete",
      "is_excluded": false,
      "object": null,
      "parameter": null,
      "service": "ExternalChannelProfile",
      "action": null,
      "type": "Action"
    },
    {
      "permissions": [
        "Operator"
      ],
      "excluded_permissions": [],
      "name": "ExternalChannelProfile_Add",
      "is_excluded": false,
      "object": null,
      "parameter": null,
      "service": "ExternalChannelProfile",
      "action": null,
      "type": "Action"
    },
    {
      "permissions": [
        "Operator"
      ],
      "excluded_permissions": [],
      "name": "ExternalChannelProfile_Update",
      "is_excluded": false,
      "object": null,
      "parameter": null,
      "service": "ExternalChannelProfile",
      "action": null,
      "type": "Action"
    }
  ],
  "type": "Action"
}