{
  "name": "permission_item_controller_messagetemplate",
  "type": "controller",
  "permission_items": [
    {
      "permissions": [
        "Operator"
      ],
      "permission_item": {
        "service": "MessageTemplate",
        "action": "Get",
        "name": "MessageTemplateGet",
        "is_excluded": false
      }
    },
    {
      "permissions": [
        "Operator"
      ],
      "permission_item": {
        "service": "MessageTemplate",
        "action": "Update",
        "name": "MessageTemplate_Update",
        "is_excluded": false
      }
    },
    {
      "permissions": [
        "Operator"
      ],
      "permission_item": {
        "service": "MessageTemplate",
        "action": "Set",
        "name": "MessageTemplate_Set",
        "is_excluded": false
      }
    }
  ]
}