{
  "permission_items": [
    {
      "permissions": [
        "Anonymous",
        "Master",
        "Operator"
      ],
      "excluded_permissions": [],
      "name": "Channel_Get",
      "service": "Channel",
      "action": "Get",
      "type": "Action"
    },
    {
      "permissions": [
        "Anonymous",
        "Master",
        "Operator"
      ],
      "excluded_permissions": [],
      "name": "Channel_List",
      "service": "Channel",
      "action": "List",
      "type": "Action"
    },
    {
      "permissions": [
        "Operator"
      ],
      "excluded_permissions": [],
      "name": "Channel_Add",
      "service": "Channel",
      "action": "Add",
      "type": "Action"
    },
    {
      "permissions": [
        "Operator"
      ],
      "excluded_permissions": [],
      "name": "Channel_Delete",
      "service": "Channel",
      "action": "Delete",
      "type": "Action"
    },
    {
      "permissions": [
        "Operator"
      ],
      "excluded_permissions": [],
      "name": "Channel_Update",
      "service": "Channel",
      "action": "Update",
      "type": "Action"
    }
  ],
  "type": "Action"
}