{"actionParams":[{"type":"KalturaHouseholdUser","description":"User details to add","isAbstract":false,"isSimpleType":false,"isComplexType":true,"isFile":false,"isEnum":false,"isStringEnum":false,"isArray":false,"isReadOnly":false,"isInsertOnly":false,"isWriteOnly":false,"properties":[{"type":"string","name":"userId","isSimpleType":true,"isComplexType":false,"isFile":false,"isEnum":false,"isStringEnum":false,"isArray":false,"isReadOnly":false,"isInsertOnly":false,"isWriteOnly":false,"description":"The identifier of the user"},{"type":"bool","name":"isMaster","isSimpleType":true,"isComplexType":false,"isFile":false,"isEnum":false,"isStringEnum":false,"isArray":false,"isReadOnly":false,"isInsertOnly":false,"isWriteOnly":false,"description":"True if the user added as master use"}],"name":"householdUser","isOptional":false}],"description":"Adds a user to household"}