{"actionParams":[{"type":"string","isSimpleType":true,"isComplexType":false,"isFile":false,"isEnum":false,"isStringEnum":false,"isArray":false,"isAbstract":false,"description":"In case type is \"announcement\", identifier should be the announcement ID. In case type is \"system\", identifier should be \"login\" (the login topic)","name":"identifier","isOptional":false},{"type":"KalturaNotificationType","description":"\"announcement\" - TV-Series topic, \"system\" - login topic","isSimpleType":false,"isComplexType":true,"isFile":false,"isEnum":true,"isStringEnum":true,"isArray":false,"isReadOnly":false,"isInsertOnly":false,"isWriteOnly":false,"constants":[{"type":"string","name":"ANNOUNCEMENT","defaultValue":"announcement","description":"","isSimpleType":true},{"type":"string","name":"SYSTEM","defaultValue":"system","description":"","isSimpleType":true}],"name":"type","isOptional":false}],"description":"TBD"}